annococo/__init__.py
annococo/coco.py
annococo/py.typed
annococo-0.0.4.dist-info/LICENSE
annococo-0.0.4.dist-info/METADATA
annococo-0.0.4.dist-info/WHEEL
annococo-0.0.4.dist-info/entry_points.txt
annococo-0.0.4.dist-info/RECORD
