Metadata-Version: 2.1
Name: annococo
Version: 0.0.4
Summary: 
License: MIT
Author: yumizu
Requires-Python: >=3.8,<=3.12.0
Classifier: License :: OSI Approved :: MIT License
Classifier: Programming Language :: Python :: 3
Classifier: Programming Language :: Python :: 3.8
Classifier: Programming Language :: Python :: 3.9
Classifier: Programming Language :: Python :: 3.10
Classifier: Programming Language :: Python :: 3.11
Classifier: Programming Language :: Python :: 3.12
Requires-Dist: pydantic (>=2.0.0,<3.0.0)
